{
  "warnings": [
    {
      "file": "/Users/shukov/Projects/CachingPlayerItem/Source/CachingPlayerItem.swift",
      "line": 50,
      "symbol": "CachingPlayerItem.delegate",
      "symbol_kind": "source.lang.swift.decl.var.instance",
      "warning": "undocumented"
    },
    {
      "file": "/Users/shukov/Projects/CachingPlayerItem/Source/CachingPlayerItem.swift",
      "line": 251,
      "symbol": "CachingPlayerItem.observeValue(forKeyPath:of:change:context:)",
      "symbol_kind": "source.lang.swift.decl.function.method.instance",
      "warning": "undocumented"
    }
  ],
  "source_directory": "/Users/shukov/Projects/CachingPlayerItem"
}